mdfl/__init__.py
mdfl/__main__.py
mdfl/parser/__init__.py
mdfl/parser/exceptions.py
mdfl/parser/utils.py
mdfl/templates/function/cookiecutter.json
mdfl/templates/function/{{ cookiecutter.name }}.function/{{ cookiecutter.name }}.mcfunction
mdfl/templates/pack/cookiecutter.json
mdfl/templates/pack/{{ cookiecutter.name }}/pack.mcmeta
mdfl-0.3.dist-info/entry_points.txt
mdfl-0.3.dist-info/WHEEL
mdfl-0.3.dist-info/METADATA
mdfl-0.3.dist-info/RECORD
