Metadata-Version: 2.1
Name: mdfl
Version: 0.3
Summary: A prototype command-line tool for creating datapacks.
License: MIT
Author: Jeremiah Boby
Author-email: mail@jeremiahboby.me
Requires-Python: >=3.8,<4.0
Classifier: License :: OSI Approved :: MIT License
Classifier: Programming Language :: Python :: 3
Classifier: Programming Language :: Python :: 3.8
Requires-Dist: cookiecutter (>=1.7.2,<2.0.0)
Requires-Dist: docopt (>=0.6.2,<0.7.0)
Requires-Dist: lark-parser (>=0.8.6,<0.9.0)
